lewansoul_lx16a_terminal.py
lewansoul_lx16a_terminal-0.1.data/data/resources/ConfigureId.ui
lewansoul_lx16a_terminal-0.1.data/data/resources/ConfigureMaxTemperature.ui
lewansoul_lx16a_terminal-0.1.data/data/resources/ConfigurePositionLimits.ui
lewansoul_lx16a_terminal-0.1.data/data/resources/ConfigurePositionOffset.ui
lewansoul_lx16a_terminal-0.1.data/data/resources/ConfigureVoltageLimits.ui
lewansoul_lx16a_terminal-0.1.data/data/resources/ServoTerminal.ui
lewansoul_lx16a_terminal-0.1.data/scripts/lewansoul_lx16a_terminal
lewansoul_lx16a_terminal-0.1.dist-info/METADATA
lewansoul_lx16a_terminal-0.1.dist-info/WHEEL
lewansoul_lx16a_terminal-0.1.dist-info/top_level.txt
lewansoul_lx16a_terminal-0.1.dist-info/RECORD
