Metadata-Version: 2.1
Name: lewansoul-lx16a-terminal
Version: 0.1
Summary: GUI to configure and control LewanSoul LX-16A servos
Home-page: https://github.com/maximkulkin/lewansoul-lx16a
Author: Maxim Kulkin
Author-email: maxim.kulkin@gmail.com
License: MIT
Platform: UNKNOWN
Classifier: Development Status :: 5 - Production/Stable
Classifier: Intended Audience :: Developers
Classifier: License :: OSI Approved :: MIT License
Classifier: Programming Language :: Python :: 3
Classifier: Programming Language :: Python :: 3.3
Classifier: Programming Language :: Python :: 3.4
Classifier: Programming Language :: Python :: 3.5
Classifier: Programming Language :: Python :: 3.6
Classifier: Programming Language :: Python :: Implementation :: CPython
Classifier: Programming Language :: Python :: Implementation :: PyPy
Requires-Dist: lewansoul-lx16a
Requires-Dist: pyserial
Requires-Dist: PyQt5
